{
  "musers": [
    {
      "name": "Леонид",
      "surname": "Голубков",
      "patronymic": "Алеексеевич",
      "type": 0,
      "number": "+7(921)-321-3214",
      "email": "lenyaGGG@mail.ru",
      "birthday": "1992-12-12",
      "id": 1
    },
    {
      "name": "Матвей",
      "surname": "Цыбулько",
      "patronymic": "Иванович",
      "type": 1,
      "number": "+7(123)-141-4211",
      "email": "MatveyCHeck@mail.ru",
      "birthday": "1984-11-10",
      "id": 2
    },
    {
      "name": "Алёна",
      "surname": "Рогозина",
      "patronymic": "Александровна",
      "type": 2,
      "number": "+7(534)-534-3432",
      "email": "Alenyvas@yandex.ru",
      "birthday": "1996-10-10",
      "id": 3
    },
    {
      "name": "Илья",
      "surname": "Голунов",
      "patronymic": "Дмитреевич",
      "type": 3,
      "number": "+7(235)-224-2343",
      "email": "Axenaxas@mail.ru",
      "birthday": "2000-11-11",
      "id": 4
    },
    {
      "name": "saddas",
      "surname": "dsadsad",
      "patronymic": "asdsads",
      "type": 0,
      "number": "+7(131)-241-2412",
      "email": "adadasd@mail.ru",
      "birthday": "1979-01-31",
      "id": 5
    },
    {
      "name": "sads",
      "surname": "dawsdas",
      "patronymic": "dassdasad",
      "type": 0,
      "number": "+7(133)-321-3214",
      "email": "sadasd@ewasds",
      "birthday": "1996-02-16",
      "id": 6
    }
  ]
}